odoo/addons/document_page_project/README.rst
odoo/addons/document_page_project/__init__.py
odoo/addons/document_page_project/__manifest__.py
odoo/addons/document_page_project/i18n/document_page_project.pot
odoo/addons/document_page_project/i18n/es.po
odoo/addons/document_page_project/i18n/he_IL.po
odoo/addons/document_page_project/i18n/hr.po
odoo/addons/document_page_project/models/__init__.py
odoo/addons/document_page_project/models/document_page.py
odoo/addons/document_page_project/models/project_project.py
odoo/addons/document_page_project/readme/CONTRIBUTORS.rst
odoo/addons/document_page_project/readme/DESCRIPTION.rst
odoo/addons/document_page_project/readme/USAGE.rst
odoo/addons/document_page_project/static/description/icon.png
odoo/addons/document_page_project/static/description/index.html
odoo/addons/document_page_project/views/document_page_views.xml
odoo/addons/document_page_project/views/project_project_views.xml
odoo13_addon_document_page_project-13.0.1.0.2.dist-info/METADATA
odoo13_addon_document_page_project-13.0.1.0.2.dist-info/WHEEL
odoo13_addon_document_page_project-13.0.1.0.2.dist-info/top_level.txt
odoo13_addon_document_page_project-13.0.1.0.2.dist-info/RECORD
